lakeflush/__init__.py
lakeflush/version.py
lakeflush/collectors/__init__.py
lakeflush/collectors/local_lake.py
lakeflush/collectors/s3_lake.py
lakeflush/core/__init__.py
lakeflush/core/collector copy.py
lakeflush/core/collector.py
lakeflush/core/event_handler.py
lakeflush/core/file_handler.py
lakeflush/core/flusher.py
lakeflush/core/gzipfile_handler.py
lakeflush/flushers/__init__.py
lakeflush/flushers/local_lake.py
lakeflush/flushers/s3_lake.py
lakeflush/utils/__init__.py
lakeflush/utils/logger.py
lakeflush/utils/metastore.py
lakeflush/utils/file/__init__.py
lakeflush/utils/file/processor.py
lakeflush/utils/file/status.py
lakeflush/utils/file/store.py
lakeflush/utils/file/type.py
lakeflush/utils/file/reader/__init__.py
lakeflush/utils/file/reader/csv copy.py
lakeflush/utils/file/reader/csv.py
lakeflush/utils/file/reader/json.py
lakeflush/utils/metadata/__init__.py
lakeflush/utils/metadata/key.py
lakeflush/utils/metadata/store.py
lakeflush/utils/s3/__init__.py
lakeflush/utils/s3/processor.py
lakeflush/utils/s3/store.py
lakeflush/utils/s3/reader/__init__.py
lakeflush/utils/s3/reader/csv.py
lakeflush/utils/s3/reader/json.py
lakeflush-0.1.0.dist-info/licenses/LICENSE
lakeflush-0.1.0.dist-info/METADATA
lakeflush-0.1.0.dist-info/WHEEL
lakeflush-0.1.0.dist-info/top_level.txt
lakeflush-0.1.0.dist-info/RECORD
