Metadata-Version: 2.4
Name: lakeflush
Version: 0.1.0
Summary: lakeflush optimizes data lakes by consolidating small files into larger bundles for big data workloads. Reduces storage overhead and improves processing efficiency.
Author-email: Abhinav Kaurav <dev@cloudindus.com>
License-Expression: Apache-2.0
Project-URL: homepage, https://github.com/cloudindus-com/lakeflush
Project-URL: source, https://github.com/cloudindus-com/lakeflush
Project-URL: issues, https://github.com/cloudindus-com/lakeflush/issues
Classifier: Development Status :: 2 - Pre-Alpha
Classifier: Intended Audience :: Developers
Classifier: Intended Audience :: Education
Classifier: Natural Language :: English
Classifier: Operating System :: OS Independent
Classifier: Programming Language :: Python
Classifier: Programming Language :: Python :: 3.11
Classifier: Programming Language :: Python :: 3.12
Classifier: Programming Language :: Python :: 3.13
Classifier: Programming Language :: Python :: Implementation :: CPython
Classifier: Programming Language :: Python :: Implementation :: PyPy
Classifier: Topic :: Software Development :: Libraries
Classifier: Topic :: Utilities
Requires-Python: >=3.9
License-File: LICENSE
Requires-Dist: watchdog==6.0.0
Provides-Extra: aws
Requires-Dist: boto3==1.38.13; extra == "aws"
Provides-Extra: test
Requires-Dist: pytest>=7.4.0; extra == "test"
Requires-Dist: pytest-cov>=3.0.0; extra == "test"
Requires-Dist: pytest-mock>=3.9.0; extra == "test"
Dynamic: license-file
